scidbpy/__init__.py
scidbpy/db.py
scidbpy/meta.py
scidbpy/schema.py
scidb_py-19.11.7.dist-info/LICENSE.txt
scidb_py-19.11.7.dist-info/METADATA
scidb_py-19.11.7.dist-info/WHEEL
scidb_py-19.11.7.dist-info/top_level.txt
scidb_py-19.11.7.dist-info/RECORD
