Metadata-Version: 2.1
Name: scidb-py
Version: 19.11.7
Summary: Python library for SciDB
Download-URL: http://github.com/Paradigm4/SciDB-Py
Author: Rares Vernica
Author-email: rvernica@gmail.com
License: AGPL-3.0
Classifier: Development Status :: 5 - Production/Stable
Classifier: Environment :: Console
Classifier: Intended Audience :: Science/Research
Classifier: License :: OSI Approved :: GNU Affero General Public License v3
Classifier: Natural Language :: English
Classifier: Programming Language :: Python :: 3.6
Classifier: Programming Language :: Python :: 3.7
Classifier: Programming Language :: Python :: 3.8
Classifier: Programming Language :: Python :: 3.9
Classifier: Programming Language :: Python :: 3.10
Classifier: Topic :: Database :: Front-Ends
Classifier: Topic :: Scientific/Engineering
License-File: LICENSE.txt
Requires-Dist: backports.weakref
Requires-Dist: enum34
Requires-Dist: numpy
Requires-Dist: pandas <=2.1.0
Requires-Dist: pyarrow <=11.0.0,>=5.0.0
Requires-Dist: requests
Requires-Dist: six
